datawindow/__init__.py
datawindow/load.py
datawindow/model.py
datawindow/preprocess.py
datawindow-0.1.1.dist-info/LICENSE.txt
datawindow-0.1.1.dist-info/METADATA
datawindow-0.1.1.dist-info/WHEEL
datawindow-0.1.1.dist-info/top_level.txt
datawindow-0.1.1.dist-info/RECORD
